odoo/addons/attribute_set_completeness/README.rst
odoo/addons/attribute_set_completeness/__init__.py
odoo/addons/attribute_set_completeness/__manifest__.py
odoo/addons/attribute_set_completeness/components/__init__.py
odoo/addons/attribute_set_completeness/components/attribute_set_owner_event_listener.py
odoo/addons/attribute_set_completeness/i18n/attribute_set_completeness.pot
odoo/addons/attribute_set_completeness/migrations/14.0.1.0.1/pre-migration.py
odoo/addons/attribute_set_completeness/models/__init__.py
odoo/addons/attribute_set_completeness/models/attribute_set.py
odoo/addons/attribute_set_completeness/models/attribute_set_completeness.py
odoo/addons/attribute_set_completeness/models/attribute_set_owner_mixin.py
odoo/addons/attribute_set_completeness/readme/CONTRIBUTORS.rst
odoo/addons/attribute_set_completeness/readme/DESCRIPTION.rst
odoo/addons/attribute_set_completeness/readme/USAGE.rst
odoo/addons/attribute_set_completeness/security/attribute_set_completeness.xml
odoo/addons/attribute_set_completeness/static/description/icon.png
odoo/addons/attribute_set_completeness/static/description/index.html
odoo/addons/attribute_set_completeness/tests/__init__.py
odoo/addons/attribute_set_completeness/tests/res_partner_event_listener.py
odoo/addons/attribute_set_completeness/tests/test_attribute_set_completeness.py
odoo/addons/attribute_set_completeness/views/attribute_set.xml
odoo/addons/attribute_set_completeness/views/attribute_set_completeness.xml
odoo14_addon_attribute_set_completeness-14.0.2.0.0.dist-info/METADATA
odoo14_addon_attribute_set_completeness-14.0.2.0.0.dist-info/WHEEL
odoo14_addon_attribute_set_completeness-14.0.2.0.0.dist-info/top_level.txt
odoo14_addon_attribute_set_completeness-14.0.2.0.0.dist-info/RECORD
